{
	"backtrace" : 1,
	"backtraceGraph" : 
	{
		"commands" : 
		[
			"add_custom_target"
		],
		"files" : 
		[
			"/home/adarsh/projects/glfw/CMakeLists.txt"
		],
		"nodes" : 
		[
			{
				"file" : 0
			},
			{
				"command" : 0,
				"file" : 0,
				"line" : 317,
				"parent" : 0
			}
		]
	},
	"folder" : 
	{
		"name" : "GLFW3"
	},
	"id" : "uninstall::@37f0cef7d816cfa7c2bb",
	"name" : "uninstall",
	"paths" : 
	{
		"build" : "/home/adarsh/projects/glfw/build",
		"source" : "/home/adarsh/projects/glfw"
	},
	"sourceGroups" : 
	[
		{
			"name" : "",
			"sourceIndexes" : 
			[
				0
			]
		},
		{
			"name" : "CMake Rules",
			"sourceIndexes" : 
			[
				1
			]
		}
	],
	"sources" : 
	[
		{
			"backtrace" : 1,
			"isGenerated" : true,
			"path" : "/home/adarsh/projects/glfw/build/CMakeFiles/uninstall",
			"sourceGroupIndex" : 0
		},
		{
			"backtrace" : 0,
			"isGenerated" : true,
			"path" : "/home/adarsh/projects/glfw/build/CMakeFiles/uninstall.rule",
			"sourceGroupIndex" : 1
		}
	],
	"type" : "UTILITY"
}
